clickhouse_insert/__init__.py
clickhouse_insert/cast_rewriter.py
clickhouse_insert/cli.py
clickhouse_insert/config_loader.py
clickhouse_insert/runner.py
insert_tools-1.0.1.dist-info/METADATA
insert_tools-1.0.1.dist-info/WHEEL
insert_tools-1.0.1.dist-info/entry_points.txt
insert_tools-1.0.1.dist-info/top_level.txt
insert_tools-1.0.1.dist-info/RECORD
