Metadata-Version: 2.4
Name: insert-tools
Version: 1.0.1
Summary: 🧩 Safe insertion of SELECT queries into ClickHouse with schema validation
Author-email: castengine <k.n.gorelov@gmail.com>
License: MIT License
Project-URL: Homepage, https://github.com/castengine/insert-tools
Project-URL: Issues, https://github.com/castengine/insert-tools/issues
Classifier: Programming Language :: Python :: 3
Classifier: Operating System :: OS Independent
Requires-Python: >=3.8
Requires-Dist: clickhouse-connect>=0.6.5
Requires-Dist: pydantic>=1.10.0
Requires-Dist: python-dotenv>=1.0.0
Requires-Dist: pyyaml>=6.0
